<?xml version="1.0" encoding="UTF-8"?>
<gfc:FC_FeatureCatalogue xmlns:gfc="http://www.isotc211.org/2005/gfc" xmlns:gco="http://www.isotc211.org/2005/gco" xmlns:gmd="http://www.isotc211.org/2005/gmd" xmlns:geonet="http://www.fao.org/geonetwork" xmlns:xsi="http://www.w3.org/2001/XMLSchema-instance" uuid="576a4046-2012-4a5a-84ad-0e5fda55d575" xsi:schemaLocation="http://www.isotc211.org/2005/gfc http://www.isotc211.org/2005/gfc/gfc.xsd">
  <gfc:name>
    <gco:CharacterString>Dictionnaire de donnees pour ouvrages sur les sentiers d’intérêt départemental</gco:CharacterString>
  </gfc:name>
  <gfc:scope>
    <gco:CharacterString>http://</gco:CharacterString>
  </gfc:scope>
  <gfc:fieldOfApplication>
    <gco:CharacterString>Dictionnaire de donnees pour ouvrages sur les sentiers d’intérêt départemental</gco:CharacterString>
  </gfc:fieldOfApplication>
  <gfc:versionNumber>
    <gco:CharacterString>v1</gco:CharacterString>
  </gfc:versionNumber>
  <gfc:versionDate>
    <gco:DateTime xmlns:gmx="http://www.isotc211.org/2005/gmx">2012-07-25T14:42:02</gco:DateTime>
  </gfc:versionDate>
  <gfc:producer>
    <gmd:CI_ResponsibleParty>
      <gmd:individualName>
        <gco:CharacterString>WATTEAU</gco:CharacterString>
      </gmd:individualName>
      <gmd:organisationName>
        <gco:CharacterString>DJECS Service Education et Sports</gco:CharacterString>
      </gmd:organisationName>
      <gmd:positionName>
        <gco:CharacterString>CHARGE DE MISSION</gco:CharacterString>
      </gmd:positionName>
      <gmd:contactInfo>
        <gmd:CI_Contact />
      </gmd:contactInfo>
      <gmd:role>
        <gmd:CI_RoleCode codeList="" codeListValue="pointOfContact" />
      </gmd:role>
    </gmd:CI_ResponsibleParty>
  </gfc:producer>
  <gfc:featureType>
    <gfc:FC_FeatureType uuid="877fbc5a-a76a-4f86-9774-f38a7cfb2734" id="">
      <gfc:typeName>
        <gco:LocalName>Nom de la propriete</gco:LocalName>
      </gfc:typeName>
      <gfc:isAbstract>
        <gco:Boolean>false</gco:Boolean>
      </gfc:isAbstract>
      <gfc:featureCatalogue xmlns:xlink="http://www.w3.org/1999/xlink" xlink:href="#" />
      <gfc:carrierOfCharacteristics>
        <gfc:FC_FeatureAttribute>
          <gfc:memberName>
            <gco:LocalName>pk_ouv</gco:LocalName>
          </gfc:memberName>
          <gfc:definition>
            <gco:CharacterString>Identifiant de l'ouvrage</gco:CharacterString>
          </gfc:definition>
          <gfc:cardinality>
            <gco:Multiplicity>
              <gco:range>
                <gco:MultiplicityRange>
                  <gco:lower>
                    <gco:Integer>0</gco:Integer>
                  </gco:lower>
                  <gco:upper>
                    <gco:UnlimitedInteger isInfinite="false" xsi:nil="false">1</gco:UnlimitedInteger>
                  </gco:upper>
                </gco:MultiplicityRange>
              </gco:range>
            </gco:Multiplicity>
          </gfc:cardinality>
          <gfc:featureType />
          <gfc:valueMeasurementUnit>
            <gml:UnitDefinition xmlns:gml="http://www.opengis.net/gml" gml:id="unknown">
              <gml:identifier codeSpace="unknown" />
            </gml:UnitDefinition>
          </gfc:valueMeasurementUnit>
          <gfc:valueType>
            <gco:TypeName>
              <gco:aName>
                <gco:CharacterString>TEXT</gco:CharacterString>
              </gco:aName>
            </gco:TypeName>
          </gfc:valueType>
        </gfc:FC_FeatureAttribute>
      </gfc:carrierOfCharacteristics>
      <gfc:carrierOfCharacteristics>
        <gfc:FC_FeatureAttribute>
          <gfc:memberName>
            <gco:LocalName>lb_iti</gco:LocalName>
          </gfc:memberName>
          <gfc:definition>
            <gco:CharacterString>Libellé de l'itinéraire sur lequel se situe l'ouvrage</gco:CharacterString>
          </gfc:definition>
          <gfc:cardinality>
            <gco:Multiplicity>
              <gco:range>
                <gco:MultiplicityRange>
                  <gco:lower>
                    <gco:Integer>0</gco:Integer>
                  </gco:lower>
                  <gco:upper>
                    <gco:UnlimitedInteger isInfinite="false" xsi:nil="false">1</gco:UnlimitedInteger>
                  </gco:upper>
                </gco:MultiplicityRange>
              </gco:range>
            </gco:Multiplicity>
          </gfc:cardinality>
          <gfc:featureType />
          <gfc:valueMeasurementUnit>
            <gml:UnitDefinition xmlns:gml="http://www.opengis.net/gml" gml:id="unknown">
              <gml:identifier codeSpace="unknown" />
            </gml:UnitDefinition>
          </gfc:valueMeasurementUnit>
          <gfc:valueType>
            <gco:TypeName>
              <gco:aName>
                <gco:CharacterString>TEXT</gco:CharacterString>
              </gco:aName>
            </gco:TypeName>
          </gfc:valueType>
        </gfc:FC_FeatureAttribute>
      </gfc:carrierOfCharacteristics>
      <gfc:carrierOfCharacteristics>
        <gfc:FC_FeatureAttribute>
          <gfc:memberName>
            <gco:LocalName>lb_iti1</gco:LocalName>
          </gfc:memberName>
          <gfc:definition>
            <gco:CharacterString>Libellé des itinérairesI sur lesquels se situent les ouvrages</gco:CharacterString>
          </gfc:definition>
          <gfc:cardinality>
            <gco:Multiplicity>
              <gco:range>
                <gco:MultiplicityRange>
                  <gco:lower>
                    <gco:Integer>0</gco:Integer>
                  </gco:lower>
                  <gco:upper>
                    <gco:UnlimitedInteger isInfinite="false" xsi:nil="false">1</gco:UnlimitedInteger>
                  </gco:upper>
                </gco:MultiplicityRange>
              </gco:range>
            </gco:Multiplicity>
          </gfc:cardinality>
          <gfc:featureType />
          <gfc:valueMeasurementUnit>
            <gml:UnitDefinition xmlns:gml="http://www.opengis.net/gml" gml:id="unknown">
              <gml:identifier codeSpace="unknown" />
            </gml:UnitDefinition>
          </gfc:valueMeasurementUnit>
          <gfc:valueType>
            <gco:TypeName>
              <gco:aName>
                <gco:CharacterString>TEXT</gco:CharacterString>
              </gco:aName>
            </gco:TypeName>
          </gfc:valueType>
        </gfc:FC_FeatureAttribute>
      </gfc:carrierOfCharacteristics>
      <gfc:carrierOfCharacteristics>
        <gfc:FC_FeatureAttribute>
          <gfc:memberName>
            <gco:LocalName>id_ouv</gco:LocalName>
          </gfc:memberName>
          <gfc:definition>
            <gco:CharacterString>Type de l'ouvrage</gco:CharacterString>
          </gfc:definition>
          <gfc:cardinality>
            <gco:Multiplicity>
              <gco:range>
                <gco:MultiplicityRange>
                  <gco:lower>
                    <gco:Integer>0</gco:Integer>
                  </gco:lower>
                  <gco:upper>
                    <gco:UnlimitedInteger isInfinite="false" xsi:nil="false">1</gco:UnlimitedInteger>
                  </gco:upper>
                </gco:MultiplicityRange>
              </gco:range>
            </gco:Multiplicity>
          </gfc:cardinality>
          <gfc:featureType />
          <gfc:valueMeasurementUnit>
            <gml:UnitDefinition xmlns:gml="http://www.opengis.net/gml" gml:id="unknown">
              <gml:identifier codeSpace="unknown" />
            </gml:UnitDefinition>
          </gfc:valueMeasurementUnit>
          <gfc:valueType>
            <gco:TypeName>
              <gco:aName>
                <gco:CharacterString>TEXT</gco:CharacterString>
              </gco:aName>
            </gco:TypeName>
          </gfc:valueType>
        </gfc:FC_FeatureAttribute>
      </gfc:carrierOfCharacteristics>
      <gfc:carrierOfCharacteristics>
        <gfc:FC_FeatureAttribute>
          <gfc:memberName>
            <gco:LocalName>lb_lieu</gco:LocalName>
          </gfc:memberName>
          <gfc:definition>
            <gco:CharacterString>Nom du lieu-dit</gco:CharacterString>
          </gfc:definition>
          <gfc:cardinality>
            <gco:Multiplicity>
              <gco:range>
                <gco:MultiplicityRange>
                  <gco:lower>
                    <gco:Integer>0</gco:Integer>
                  </gco:lower>
                  <gco:upper>
                    <gco:UnlimitedInteger isInfinite="false" xsi:nil="false">1</gco:UnlimitedInteger>
                  </gco:upper>
                </gco:MultiplicityRange>
              </gco:range>
            </gco:Multiplicity>
          </gfc:cardinality>
          <gfc:featureType />
          <gfc:valueMeasurementUnit>
            <gml:UnitDefinition xmlns:gml="http://www.opengis.net/gml" gml:id="unknown">
              <gml:identifier codeSpace="unknown" />
            </gml:UnitDefinition>
          </gfc:valueMeasurementUnit>
          <gfc:valueType>
            <gco:TypeName>
              <gco:aName>
                <gco:CharacterString>TEXT</gco:CharacterString>
              </gco:aName>
            </gco:TypeName>
          </gfc:valueType>
        </gfc:FC_FeatureAttribute>
      </gfc:carrierOfCharacteristics>
      <gfc:carrierOfCharacteristics>
        <gfc:FC_FeatureAttribute>
          <gfc:memberName>
            <gco:LocalName>insee</gco:LocalName>
          </gfc:memberName>
          <gfc:definition>
            <gco:CharacterString>Code INSEE sur laquelle se situe l'ouvrage</gco:CharacterString>
          </gfc:definition>
          <gfc:cardinality>
            <gco:Multiplicity>
              <gco:range>
                <gco:MultiplicityRange>
                  <gco:lower>
                    <gco:Integer>0</gco:Integer>
                  </gco:lower>
                  <gco:upper>
                    <gco:UnlimitedInteger isInfinite="false" xsi:nil="false">1</gco:UnlimitedInteger>
                  </gco:upper>
                </gco:MultiplicityRange>
              </gco:range>
            </gco:Multiplicity>
          </gfc:cardinality>
          <gfc:featureType />
          <gfc:valueMeasurementUnit>
            <gml:UnitDefinition xmlns:gml="http://www.opengis.net/gml" gml:id="unknown">
              <gml:identifier codeSpace="unknown" />
            </gml:UnitDefinition>
          </gfc:valueMeasurementUnit>
          <gfc:valueType>
            <gco:TypeName>
              <gco:aName>
                <gco:CharacterString>TEXT</gco:CharacterString>
              </gco:aName>
            </gco:TypeName>
          </gfc:valueType>
        </gfc:FC_FeatureAttribute>
      </gfc:carrierOfCharacteristics>
      <gfc:carrierOfCharacteristics>
        <gfc:FC_FeatureAttribute>
          <gfc:memberName>
            <gco:LocalName>long</gco:LocalName>
          </gfc:memberName>
          <gfc:definition>
            <gco:CharacterString>Longueur de l'ouvrage en m</gco:CharacterString>
          </gfc:definition>
          <gfc:cardinality>
            <gco:Multiplicity>
              <gco:range>
                <gco:MultiplicityRange>
                  <gco:lower>
                    <gco:Integer>0</gco:Integer>
                  </gco:lower>
                  <gco:upper>
                    <gco:UnlimitedInteger isInfinite="false" xsi:nil="false">1</gco:UnlimitedInteger>
                  </gco:upper>
                </gco:MultiplicityRange>
              </gco:range>
            </gco:Multiplicity>
          </gfc:cardinality>
          <gfc:featureType />
          <gfc:valueMeasurementUnit>
            <gml:UnitDefinition xmlns:gml="http://www.opengis.net/gml" gml:id="unknown">
              <gml:identifier codeSpace="unknown" />
            </gml:UnitDefinition>
          </gfc:valueMeasurementUnit>
          <gfc:valueType>
            <gco:TypeName>
              <gco:aName>
                <gco:CharacterString>INTEGER</gco:CharacterString>
              </gco:aName>
            </gco:TypeName>
          </gfc:valueType>
        </gfc:FC_FeatureAttribute>
      </gfc:carrierOfCharacteristics>
      <gfc:carrierOfCharacteristics>
        <gfc:FC_FeatureAttribute>
          <gfc:memberName>
            <gco:LocalName>larg</gco:LocalName>
          </gfc:memberName>
          <gfc:definition>
            <gco:CharacterString>Largeur de l'ouvrage en m</gco:CharacterString>
          </gfc:definition>
          <gfc:cardinality>
            <gco:Multiplicity>
              <gco:range>
                <gco:MultiplicityRange>
                  <gco:lower>
                    <gco:Integer>0</gco:Integer>
                  </gco:lower>
                  <gco:upper>
                    <gco:UnlimitedInteger isInfinite="false" xsi:nil="false">1</gco:UnlimitedInteger>
                  </gco:upper>
                </gco:MultiplicityRange>
              </gco:range>
            </gco:Multiplicity>
          </gfc:cardinality>
          <gfc:featureType />
          <gfc:valueMeasurementUnit>
            <gml:UnitDefinition xmlns:gml="http://www.opengis.net/gml" gml:id="unknown">
              <gml:identifier codeSpace="unknown" />
            </gml:UnitDefinition>
          </gfc:valueMeasurementUnit>
          <gfc:valueType>
            <gco:TypeName>
              <gco:aName>
                <gco:CharacterString>INTEGER</gco:CharacterString>
              </gco:aName>
            </gco:TypeName>
          </gfc:valueType>
        </gfc:FC_FeatureAttribute>
      </gfc:carrierOfCharacteristics>
      <gfc:carrierOfCharacteristics>
        <gfc:FC_FeatureAttribute>
          <gfc:memberName>
            <gco:LocalName>id_materiaux</gco:LocalName>
          </gfc:memberName>
          <gfc:definition>
            <gco:CharacterString>Matérieux de l'ouvrage</gco:CharacterString>
          </gfc:definition>
          <gfc:cardinality>
            <gco:Multiplicity>
              <gco:range>
                <gco:MultiplicityRange>
                  <gco:lower>
                    <gco:Integer>0</gco:Integer>
                  </gco:lower>
                  <gco:upper>
                    <gco:UnlimitedInteger isInfinite="false" xsi:nil="false">1</gco:UnlimitedInteger>
                  </gco:upper>
                </gco:MultiplicityRange>
              </gco:range>
            </gco:Multiplicity>
          </gfc:cardinality>
          <gfc:featureType />
          <gfc:valueMeasurementUnit>
            <gml:UnitDefinition xmlns:gml="http://www.opengis.net/gml" gml:id="unknown">
              <gml:identifier codeSpace="unknown" />
            </gml:UnitDefinition>
          </gfc:valueMeasurementUnit>
          <gfc:valueType>
            <gco:TypeName>
              <gco:aName>
                <gco:CharacterString>TEXT</gco:CharacterString>
              </gco:aName>
            </gco:TypeName>
          </gfc:valueType>
        </gfc:FC_FeatureAttribute>
      </gfc:carrierOfCharacteristics>
      <gfc:carrierOfCharacteristics>
        <gfc:FC_FeatureAttribute>
          <gfc:memberName>
            <gco:LocalName>z</gco:LocalName>
          </gfc:memberName>
          <gfc:definition>
            <gco:CharacterString>altitude en m</gco:CharacterString>
          </gfc:definition>
          <gfc:cardinality>
            <gco:Multiplicity>
              <gco:range>
                <gco:MultiplicityRange>
                  <gco:lower>
                    <gco:Integer>0</gco:Integer>
                  </gco:lower>
                  <gco:upper>
                    <gco:UnlimitedInteger isInfinite="false" xsi:nil="false">1</gco:UnlimitedInteger>
                  </gco:upper>
                </gco:MultiplicityRange>
              </gco:range>
            </gco:Multiplicity>
          </gfc:cardinality>
          <gfc:featureType />
          <gfc:valueMeasurementUnit>
            <gml:UnitDefinition xmlns:gml="http://www.opengis.net/gml" gml:id="unknown">
              <gml:identifier codeSpace="unknown" />
            </gml:UnitDefinition>
          </gfc:valueMeasurementUnit>
          <gfc:valueType>
            <gco:TypeName>
              <gco:aName>
                <gco:CharacterString>INTEGER</gco:CharacterString>
              </gco:aName>
            </gco:TypeName>
          </gfc:valueType>
        </gfc:FC_FeatureAttribute>
      </gfc:carrierOfCharacteristics>
      <gfc:carrierOfCharacteristics>
        <gfc:FC_FeatureAttribute>
          <gfc:memberName>
            <gco:LocalName>rq</gco:LocalName>
          </gfc:memberName>
          <gfc:definition>
            <gco:CharacterString>Observations</gco:CharacterString>
          </gfc:definition>
          <gfc:cardinality>
            <gco:Multiplicity>
              <gco:range>
                <gco:MultiplicityRange>
                  <gco:lower>
                    <gco:Integer>0</gco:Integer>
                  </gco:lower>
                  <gco:upper>
                    <gco:UnlimitedInteger isInfinite="true" xsi:nil="true" />
                  </gco:upper>
                </gco:MultiplicityRange>
              </gco:range>
            </gco:Multiplicity>
          </gfc:cardinality>
          <gfc:valueType>
            <gco:TypeName>
              <gco:aName>
                <gco:CharacterString>TEXT</gco:CharacterString>
              </gco:aName>
            </gco:TypeName>
          </gfc:valueType>
        </gfc:FC_FeatureAttribute>
      </gfc:carrierOfCharacteristics>
      <gfc:carrierOfCharacteristics>
        <gfc:FC_FeatureAttribute>
          <gfc:memberName>
            <gco:LocalName>etat</gco:LocalName>
          </gfc:memberName>
          <gfc:definition>
            <gco:CharacterString>Etat de l'ouvrage (géré par NW)</gco:CharacterString>
          </gfc:definition>
          <gfc:cardinality>
            <gco:Multiplicity>
              <gco:range>
                <gco:MultiplicityRange>
                  <gco:lower>
                    <gco:Integer>0</gco:Integer>
                  </gco:lower>
                  <gco:upper>
                    <gco:UnlimitedInteger isInfinite="true" xsi:nil="true" />
                  </gco:upper>
                </gco:MultiplicityRange>
              </gco:range>
            </gco:Multiplicity>
          </gfc:cardinality>
          <gfc:valueType>
            <gco:TypeName>
              <gco:aName>
                <gco:CharacterString>TEXT</gco:CharacterString>
              </gco:aName>
            </gco:TypeName>
          </gfc:valueType>
        </gfc:FC_FeatureAttribute>
      </gfc:carrierOfCharacteristics>
      <gfc:carrierOfCharacteristics>
        <gfc:FC_FeatureAttribute>
          <gfc:memberName>
            <gco:LocalName>id_interv</gco:LocalName>
          </gfc:memberName>
          <gfc:definition>
            <gco:CharacterString>Producteur des données</gco:CharacterString>
          </gfc:definition>
          <gfc:cardinality>
            <gco:Multiplicity>
              <gco:range>
                <gco:MultiplicityRange>
                  <gco:lower>
                    <gco:Integer>0</gco:Integer>
                  </gco:lower>
                  <gco:upper>
                    <gco:UnlimitedInteger isInfinite="false" xsi:nil="false">1</gco:UnlimitedInteger>
                  </gco:upper>
                </gco:MultiplicityRange>
              </gco:range>
            </gco:Multiplicity>
          </gfc:cardinality>
          <gfc:featureType />
          <gfc:valueMeasurementUnit>
            <gml:UnitDefinition xmlns:gml="http://www.opengis.net/gml" gml:id="unknown">
              <gml:identifier codeSpace="unknown" />
            </gml:UnitDefinition>
          </gfc:valueMeasurementUnit>
          <gfc:valueType>
            <gco:TypeName>
              <gco:aName>
                <gco:CharacterString>texte</gco:CharacterString>
              </gco:aName>
            </gco:TypeName>
          </gfc:valueType>
        </gfc:FC_FeatureAttribute>
      </gfc:carrierOfCharacteristics>
      <gfc:carrierOfCharacteristics>
        <gfc:FC_FeatureAttribute>
          <gfc:memberName>
            <gco:LocalName>dt_saisie</gco:LocalName>
          </gfc:memberName>
          <gfc:definition>
            <gco:CharacterString>Date de numérisation (aaaammjj)</gco:CharacterString>
          </gfc:definition>
          <gfc:cardinality>
            <gco:Multiplicity>
              <gco:range>
                <gco:MultiplicityRange>
                  <gco:lower>
                    <gco:Integer>0</gco:Integer>
                  </gco:lower>
                  <gco:upper>
                    <gco:UnlimitedInteger isInfinite="false" xsi:nil="false">1</gco:UnlimitedInteger>
                  </gco:upper>
                </gco:MultiplicityRange>
              </gco:range>
            </gco:Multiplicity>
          </gfc:cardinality>
          <gfc:featureType />
          <gfc:valueMeasurementUnit>
            <gml:UnitDefinition xmlns:gml="http://www.opengis.net/gml" gml:id="unknown">
              <gml:identifier codeSpace="unknown" />
            </gml:UnitDefinition>
          </gfc:valueMeasurementUnit>
          <gfc:valueType>
            <gco:TypeName>
              <gco:aName>
                <gco:CharacterString>TEXT</gco:CharacterString>
              </gco:aName>
            </gco:TypeName>
          </gfc:valueType>
        </gfc:FC_FeatureAttribute>
      </gfc:carrierOfCharacteristics>
      <gfc:carrierOfCharacteristics>
        <gfc:FC_FeatureAttribute>
          <gfc:memberName>
            <gco:LocalName>rf_precis</gco:LocalName>
          </gfc:memberName>
          <gfc:definition>
            <gco:CharacterString>Précision de la numérisation</gco:CharacterString>
          </gfc:definition>
          <gfc:cardinality>
            <gco:Multiplicity>
              <gco:range>
                <gco:MultiplicityRange>
                  <gco:lower>
                    <gco:Integer>0</gco:Integer>
                  </gco:lower>
                  <gco:upper>
                    <gco:UnlimitedInteger isInfinite="false" xsi:nil="false">1</gco:UnlimitedInteger>
                  </gco:upper>
                </gco:MultiplicityRange>
              </gco:range>
            </gco:Multiplicity>
          </gfc:cardinality>
          <gfc:featureType />
          <gfc:valueMeasurementUnit>
            <gml:UnitDefinition xmlns:gml="http://www.opengis.net/gml" gml:id="unknown">
              <gml:identifier codeSpace="unknown" />
            </gml:UnitDefinition>
          </gfc:valueMeasurementUnit>
          <gfc:listedValue>
            <gfc:FC_ListedValue>
              <gfc:label>
                <gco:CharacterString>Précision inconnue</gco:CharacterString>
              </gfc:label>
              <gfc:code>
                <gco:CharacterString>0</gco:CharacterString>
              </gfc:code>
            </gfc:FC_ListedValue>
          </gfc:listedValue>
          <gfc:listedValue>
            <gfc:FC_ListedValue>
              <gfc:label>
                <gco:CharacterString>Précision cm</gco:CharacterString>
              </gfc:label>
              <gfc:code>
                <gco:CharacterString>11</gco:CharacterString>
              </gfc:code>
            </gfc:FC_ListedValue>
          </gfc:listedValue>
          <gfc:listedValue>
            <gfc:FC_ListedValue>
              <gfc:label>
                <gco:CharacterString>Précision m</gco:CharacterString>
              </gfc:label>
              <gfc:code>
                <gco:CharacterString>12</gco:CharacterString>
              </gfc:code>
            </gfc:FC_ListedValue>
          </gfc:listedValue>
          <gfc:listedValue>
            <gfc:FC_ListedValue>
              <gfc:label>
                <gco:CharacterString>Précision dam</gco:CharacterString>
              </gfc:label>
              <gfc:code>
                <gco:CharacterString>13</gco:CharacterString>
              </gfc:code>
            </gfc:FC_ListedValue>
          </gfc:listedValue>
          <gfc:listedValue>
            <gfc:FC_ListedValue>
              <gfc:label>
                <gco:CharacterString>Précision km</gco:CharacterString>
              </gfc:label>
              <gfc:code>
                <gco:CharacterString>14</gco:CharacterString>
              </gfc:code>
            </gfc:FC_ListedValue>
          </gfc:listedValue>
          <gfc:valueType>
            <gco:TypeName>
              <gco:aName>
                <gco:CharacterString>TEXT</gco:CharacterString>
              </gco:aName>
            </gco:TypeName>
          </gfc:valueType>
        </gfc:FC_FeatureAttribute>
      </gfc:carrierOfCharacteristics>
    </gfc:FC_FeatureType>
  </gfc:featureType>
</gfc:FC_FeatureCatalogue>

