<?xml version="1.0" encoding="UTF-8"?>
<gmd:MD_Metadata xmlns:gmd="http://www.isotc211.org/2005/gmd" xmlns:fo="http://www.w3.org/1999/XSL/Format" xmlns:map="urn:brgm:mapping" xmlns:xsi="http://www.w3.org/2001/XMLSchema-instance" xmlns:xlink="http://www.w3.org/1999/xlink" xmlns:gml="http://www.opengis.net/gml" xmlns:gts="http://www.isotc211.org/2005/gts" xmlns:gmx="http://www.isotc211.org/2005/gmx" xmlns:gfc="http://www.isotc211.org/2005/gfc" xmlns:gco="http://www.isotc211.org/2005/gco" xmlns:geonet="http://www.fao.org/geonetwork" xsi:schemaLocation="http://www.isotc211.org/2005/gmd ../schemas/iso19139fra/gmd/gmd.xsd">
  <gmd:fileIdentifier>
    <gco:CharacterString>{BA583C58-C287-4CE0-B601-A86CD75C63B9}</gco:CharacterString>
  </gmd:fileIdentifier>
  <gmd:language>
    <gmd:LanguageCode codeList="http://www.loc.gov/standards/iso639-2/" codeListValue="fre" />
  </gmd:language>
  <gmd:characterSet>
    <gmd:MD_CharacterSetCode codeList="http://standards.iso.org/ittf/PubliclyAvailableStandards/ISO_19139_Schemas/resources/Codelist/ML_gmxCodelists.xml#MD_CharacterSetCode" codeListValue="utf8" />
  </gmd:characterSet>
  <gmd:hierarchyLevel>
    <gmd:MD_ScopeCode codeList="http://standards.iso.org/ittf/PubliclyAvailableStandards/ISO_19139_Schemas/resources/Codelist/ML_gmxCodelists.xml#MD_ScopeCode" codeListValue="feature" />
  </gmd:hierarchyLevel>
  <gmd:hierarchyLevelName>
    <gco:CharacterString>feature</gco:CharacterString>
  </gmd:hierarchyLevelName>
  <gmd:contact>
    <gmd:CI_ResponsibleParty>
      <gmd:individualName gco:nilReason="missing">
        <gco:CharacterString />
      </gmd:individualName>
      <gmd:organisationName gco:nilReason="missing">
        <gco:CharacterString />
      </gmd:organisationName>
      <gmd:positionName gco:nilReason="missing">
        <gco:CharacterString />
      </gmd:positionName>
      <gmd:contactInfo>
        <gmd:CI_Contact>
          <gmd:phone>
            <gmd:CI_Telephone>
              <gmd:voice gco:nilReason="missing">
                <gco:CharacterString />
              </gmd:voice>
              <gmd:facsimile gco:nilReason="missing">
                <gco:CharacterString />
              </gmd:facsimile>
            </gmd:CI_Telephone>
          </gmd:phone>
          <gmd:address>
            <gmd:CI_Address>
              <gmd:deliveryPoint gco:nilReason="missing">
                <gco:CharacterString />
              </gmd:deliveryPoint>
              <gmd:city gco:nilReason="missing">
                <gco:CharacterString />
              </gmd:city>
              <gmd:administrativeArea gco:nilReason="missing">
                <gco:CharacterString />
              </gmd:administrativeArea>
              <gmd:postalCode gco:nilReason="missing">
                <gco:CharacterString />
              </gmd:postalCode>
              <gmd:country gco:nilReason="missing">
                <gco:CharacterString />
              </gmd:country>
              <gmd:electronicMailAddress gco:nilReason="missing">
                <gco:CharacterString />
              </gmd:electronicMailAddress>
            </gmd:CI_Address>
          </gmd:address>
        </gmd:CI_Contact>
      </gmd:contactInfo>
      <gmd:role>
        <gmd:CI_RoleCode xmlns:fra="http://www.cnig.gouv.fr/2005/fra" codeList="http://standards.iso.org/ittf/PubliclyAvailableStandards/ISO_19139_Schemas/resources/Codelist/ML_gmxCodelists.xml#CI_RoleCode" codeListValue="pointOfContact" />
      </gmd:role>
    </gmd:CI_ResponsibleParty>
  </gmd:contact>
  <gmd:metadataStandardName>
    <gco:CharacterString xmlns:srv="http://www.isotc211.org/2005/srv">ISO 19115:2003/19139</gco:CharacterString>
  </gmd:metadataStandardName>
  <gmd:metadataStandardVersion>
    <gco:CharacterString xmlns:srv="http://www.isotc211.org/2005/srv">1.0</gco:CharacterString>
  </gmd:metadataStandardVersion>
  <gmd:referenceSystemInfo>
    <gmd:MD_ReferenceSystem>
      <gmd:referenceSystemIdentifier>
        <gmd:RS_Identifier>
          <gmd:code>
            <gco:CharacterString>RGF_1993_Lambert_93GCS_RGF_1993</gco:CharacterString>
          </gmd:code>
        </gmd:RS_Identifier>
      </gmd:referenceSystemIdentifier>
    </gmd:MD_ReferenceSystem>
  </gmd:referenceSystemInfo>
  <gmd:identificationInfo>
    <gmd:MD_DataIdentification>
      <gmd:citation>
        <gmd:CI_Citation>
          <gmd:title>
            <gco:CharacterString>accés plage</gco:CharacterString>
          </gmd:title>
          <gmd:alternateTitle gco:nilReason="missing">
            <gco:CharacterString />
          </gmd:alternateTitle>
          <gmd:edition gco:nilReason="missing">
            <gco:CharacterString />
          </gmd:edition>
        </gmd:CI_Citation>
      </gmd:citation>
      <gmd:abstract>
        <gco:CharacterString>localisation des différents types d'accès plage dans les sites plans plages validés par le MO. 3 types de valeurs :
- accès plage autorisé
- accès plage toléré
- accès plage sauvage</gco:CharacterString>
      </gmd:abstract>
      <gmd:purpose>
        <gco:CharacterString>L'objectif de cette donnée est de connaître les différentes connections qu'il existe entre l'arrière dune (c'est à dire les parkings) et la plage. Permet de définir des zones d'action prioritaire pour la gestion des flux sur les sites. Intérêt en terme de protection du milieu dunaire</gco:CharacterString>
      </gmd:purpose>
      <gmd:status>
        <gmd:MD_ProgressCode codeList="http://standards.iso.org/ittf/PubliclyAvailableStandards/ISO_19139_Schemas/resources/Codelist/ML_gmxCodelists.xml#MD_ProgressCode" codeListValue="onGoing" />
      </gmd:status>
      <gmd:pointOfContact>
        <gmd:CI_ResponsibleParty>
          <gmd:individualName gco:nilReason="missing">
            <gco:CharacterString />
          </gmd:individualName>
          <gmd:organisationName gco:nilReason="missing">
            <gco:CharacterString />
          </gmd:organisationName>
          <gmd:positionName gco:nilReason="missing">
            <gco:CharacterString />
          </gmd:positionName>
          <gmd:contactInfo>
            <gmd:CI_Contact>
              <gmd:phone>
                <gmd:CI_Telephone>
                  <gmd:voice gco:nilReason="missing">
                    <gco:CharacterString />
                  </gmd:voice>
                  <gmd:facsimile gco:nilReason="missing">
                    <gco:CharacterString />
                  </gmd:facsimile>
                </gmd:CI_Telephone>
              </gmd:phone>
              <gmd:address>
                <gmd:CI_Address>
                  <gmd:deliveryPoint gco:nilReason="missing">
                    <gco:CharacterString />
                  </gmd:deliveryPoint>
                  <gmd:city gco:nilReason="missing">
                    <gco:CharacterString />
                  </gmd:city>
                  <gmd:administrativeArea gco:nilReason="missing">
                    <gco:CharacterString />
                  </gmd:administrativeArea>
                  <gmd:postalCode gco:nilReason="missing">
                    <gco:CharacterString />
                  </gmd:postalCode>
                  <gmd:country gco:nilReason="missing">
                    <gco:CharacterString />
                  </gmd:country>
                  <gmd:electronicMailAddress gco:nilReason="missing">
                    <gco:CharacterString />
                  </gmd:electronicMailAddress>
                </gmd:CI_Address>
              </gmd:address>
            </gmd:CI_Contact>
          </gmd:contactInfo>
          <gmd:role>
            <gmd:CI_RoleCode codeListValue="originator" codeList="http://standards.iso.org/ittf/PubliclyAvailableStandards/ISO_19139_Schemas/resources/Codelist/ML_gmxCodelists.xml#CI_RoleCode" />
          </gmd:role>
        </gmd:CI_ResponsibleParty>
      </gmd:pointOfContact>
      <gmd:resourceMaintenance>
        <gmd:MD_MaintenanceInformation>
          <gmd:maintenanceAndUpdateFrequency>
            <gmd:MD_MaintenanceFrequencyCode codeList="http://standards.iso.org/ittf/PubliclyAvailableStandards/ISO_19139_Schemas/resources/Codelist/ML_gmxCodelists.xml#MD_MaintenanceFrequencyCode" codeListValue="asNeeded" />
          </gmd:maintenanceAndUpdateFrequency>
        </gmd:MD_MaintenanceInformation>
      </gmd:resourceMaintenance>
      <gmd:resourceConstraints>
        <gmd:MD_SecurityConstraints>
          <gmd:useLimitation gco:nilReason="missing">
            <gco:CharacterString />
          </gmd:useLimitation>
          <gmd:classification>
            <gmd:MD_ClassificationCode codeList="http://standards.iso.org/ittf/PubliclyAvailableStandards/ISO_19139_Schemas/resources/Codelist/ML_gmxCodelists.xml#MD_ClassificationCode" codeListValue="" />
          </gmd:classification>
          <gmd:classificationSystem gco:nilReason="missing">
            <gco:CharacterString />
          </gmd:classificationSystem>
          <gmd:handlingDescription gco:nilReason="missing">
            <gco:CharacterString />
          </gmd:handlingDescription>
        </gmd:MD_SecurityConstraints>
      </gmd:resourceConstraints>
      <gmd:spatialRepresentationType>
        <gmd:MD_SpatialRepresentationTypeCode codeList="http://standards.iso.org/ittf/PubliclyAvailableStandards/ISO_19139_Schemas/resources/Codelist/ML_gmxCodelists.xml#MD_SpatialRepresentationTypeCode" codeListValue="vector" />
      </gmd:spatialRepresentationType>
      <gmd:language>
        <gmd:LanguageCode codeList="http://www.loc.gov/standards/iso639-2/" codeListValue="fre" />
      </gmd:language>
      <gmd:topicCategory>
        <gmd:CI_DateTypeCode codeListValue="" codeList="http://standards.iso.org/ittf/PubliclyAvailableStandards/ISO_19139_Schemas/resources/Codelist/ML_gmxCodelists.xml#CI_DateTypeCode" />
      </gmd:topicCategory>
      <gmd:environmentDescription>
        <gco:CharacterString>Microsoft Windows 2000 Version 5.2 (Build 3790) Service Pack 2; ESRI ArcCatalog 9.2.4.1420</gco:CharacterString>
      </gmd:environmentDescription>
      <gmd:extent>
        <gmd:EX_Extent>
          <gmd:description>
            <gco:CharacterString>Région aquitaine</gco:CharacterString>
          </gmd:description>
          <gmd:geographicElement>
            <gmd:EX_GeographicBoundingBox>
              <gmd:westBoundLongitude>
                <gco:Decimal>-1.956821</gco:Decimal>
              </gmd:westBoundLongitude>
              <gmd:eastBoundLongitude>
                <gco:Decimal>-0.921584</gco:Decimal>
              </gmd:eastBoundLongitude>
              <gmd:southBoundLatitude>
                <gco:Decimal>43.374253</gco:Decimal>
              </gmd:southBoundLatitude>
              <gmd:northBoundLatitude>
                <gco:Decimal>45.567589</gco:Decimal>
              </gmd:northBoundLatitude>
            </gmd:EX_GeographicBoundingBox>
          </gmd:geographicElement>
        </gmd:EX_Extent>
      </gmd:extent>
      <gmd:supplementalInformation gco:nilReason="missing">
        <gco:CharacterString />
      </gmd:supplementalInformation>
    </gmd:MD_DataIdentification>
  </gmd:identificationInfo>
  <gmd:distributionInfo>
    <gmd:MD_Distribution>
      <gmd:distributionFormat>
        <gmd:MD_Format>
          <gmd:name>
            <gco:CharacterString>Fichier de formes</gco:CharacterString>
          </gmd:name>
          <gmd:version gco:nilReason="missing">
            <gco:CharacterString />
          </gmd:version>
        </gmd:MD_Format>
      </gmd:distributionFormat>
      <gmd:distributor>
        <gmd:MD_Distributor>
          <gmd:distributorContact gco:nilReason="Unknown" />
          <gmd:distributionOrderProcess>
            <gmd:MD_StandardOrderProcess>
              <gmd:fees gco:nilReason="missing">
                <gco:CharacterString />
              </gmd:fees>
              <gmd:orderingInstructions gco:nilReason="missing">
                <gco:CharacterString />
              </gmd:orderingInstructions>
              <gmd:turnaround gco:nilReason="missing">
                <gco:CharacterString />
              </gmd:turnaround>
            </gmd:MD_StandardOrderProcess>
          </gmd:distributionOrderProcess>
        </gmd:MD_Distributor>
      </gmd:distributor>
      <gmd:transferOptions>
        <gmd:MD_DigitalTransferOptions>
          <gmd:onLine>
            <gmd:CI_OnlineResource>
              <gmd:linkage>
                <gmd:URL>file://\\SSIG042\D\EXPORT_GIP_LITTORAL\shape_L93\acc_plge.shp</gmd:URL>
              </gmd:linkage>
              <gmd:protocol>
                <gco:CharacterString>file</gco:CharacterString>
              </gmd:protocol>
              <gmd:name>
                <gco:CharacterString>acc_plge</gco:CharacterString>
              </gmd:name>
              <gmd:description>
                <gco:CharacterString>Données téléchargeables</gco:CharacterString>
              </gmd:description>
            </gmd:CI_OnlineResource>
          </gmd:onLine>
          <gmd:offLine>
            <gmd:MD_Medium>
              <gmd:name />
            </gmd:MD_Medium>
          </gmd:offLine>
        </gmd:MD_DigitalTransferOptions>
      </gmd:transferOptions>
    </gmd:MD_Distribution>
  </gmd:distributionInfo>
  <gmd:dataQualityInfo>
    <gmd:DQ_DataQuality>
      <gmd:scope>
        <gmd:DQ_Scope>
          <gmd:level>
            <gmd:MD_ScopeCode codeList="http://standards.iso.org/ittf/PubliclyAvailableStandards/ISO_19139_Schemas/resources/Codelist/ML_gmxCodelists.xml#MD_ScopeCode" codeListValue="feature" />
          </gmd:level>
        </gmd:DQ_Scope>
      </gmd:scope>
      <gmd:lineage>
        <gmd:LI_Lineage>
          <gmd:statement gco:nilReason="missing">
            <gco:CharacterString />
          </gmd:statement>
          <gmd:source>
            <gmd:LI_Source>
              <gmd:description>
                <gco:CharacterString>Données issues des bases de données historiques de l'ONF en sa qualité de gestionnaire des sites rétro littoraux. Utilisation des données de la BD TOPO IGN 2008</gco:CharacterString>
              </gmd:description>
              <gmd:scaleDenominator>
                <gmd:MD_RepresentativeFraction>
                  <gmd:denominator>
                    <gco:Integer>2000</gco:Integer>
                  </gmd:denominator>
                </gmd:MD_RepresentativeFraction>
              </gmd:scaleDenominator>
            </gmd:LI_Source>
          </gmd:source>
        </gmd:LI_Lineage>
      </gmd:lineage>
    </gmd:DQ_DataQuality>
  </gmd:dataQualityInfo>
  <gmd:metadataConstraints>
    <gmd:MD_LegalConstraints>
      <gmd:accessConstraints>
        <gmd:MD_RestrictionCode codeListValue="otherRestrictions" codeList="http://standards.iso.org/ittf/PubliclyAvailableStandards/ISO_19139_Schemas/resources/Codelist/ML_gmxCodelists.xml#MD_RestrictionCode" />
      </gmd:accessConstraints>
      <gmd:otherConstraints>
        <gco:CharacterString>A définir par le MO</gco:CharacterString>
      </gmd:otherConstraints>
    </gmd:MD_LegalConstraints>
  </gmd:metadataConstraints>
  <gmd:metadataConstraints>
    <gmd:MD_LegalConstraints>
      <gmd:accessConstraints>
        <gmd:MD_RestrictionCode codeListValue="otherRestrictions" codeList="http://standards.iso.org/ittf/PubliclyAvailableStandards/ISO_19139_Schemas/resources/Codelist/ML_gmxCodelists.xml#MD_RestrictionCode" />
      </gmd:accessConstraints>
      <gmd:otherConstraints>
        <gco:CharacterString>A définir par le MO</gco:CharacterString>
      </gmd:otherConstraints>
    </gmd:MD_LegalConstraints>
  </gmd:metadataConstraints>
  <gmd:metadataConstraints>
    <gmd:MD_SecurityConstraints>
      <gmd:useLimitation gco:nilReason="missing">
        <gco:CharacterString />
      </gmd:useLimitation>
      <gmd:classification>
        <gmd:MD_ClassificationCode codeList="http://standards.iso.org/ittf/PubliclyAvailableStandards/ISO_19139_Schemas/resources/Codelist/ML_gmxCodelists.xml#MD_ClassificationCode" codeListValue="" />
      </gmd:classification>
      <gmd:classificationSystem gco:nilReason="missing">
        <gco:CharacterString />
      </gmd:classificationSystem>
      <gmd:handlingDescription gco:nilReason="missing">
        <gco:CharacterString />
      </gmd:handlingDescription>
    </gmd:MD_SecurityConstraints>
  </gmd:metadataConstraints>
</gmd:MD_Metadata>

